vtelem/__init__.py
vtelem/__main__.py
vtelem/app.py
vtelem/dev_requirements.txt
vtelem/entry.py
vtelem/mtu.py
vtelem/names.py
vtelem/py.typed
vtelem/requirements.txt
vtelem/channel/__init__.py
vtelem/channel/environment.py
vtelem/channel/framer.py
vtelem/channel/group.py
vtelem/channel/group_registry.py
vtelem/channel/registry.py
vtelem/classes/__init__.py
vtelem/classes/byte_buffer.py
vtelem/classes/data_cache.py
vtelem/classes/event_queue.py
vtelem/classes/http_request_mapper.py
vtelem/classes/metered_queue.py
vtelem/classes/serdes.py
vtelem/classes/state.py
vtelem/classes/state_machine.py
vtelem/classes/time_entity.py
vtelem/classes/time_keeper.py
vtelem/classes/type_primitive.py
vtelem/classes/udp_client_manager.py
vtelem/classes/user_enum.py
vtelem/client/__init__.py
vtelem/client/file.py
vtelem/client/socket.py
vtelem/client/tcp.py
vtelem/client/udp.py
vtelem/client/websocket.py
vtelem/daemon/__init__.py
vtelem/daemon/command_queue.py
vtelem/daemon/event_loop.py
vtelem/daemon/http.py
vtelem/daemon/manager.py
vtelem/daemon/queue.py
vtelem/daemon/synchronous.py
vtelem/daemon/tcp_telemetry.py
vtelem/daemon/telemetry.py
vtelem/daemon/websocket.py
vtelem/daemon/websocket_telemetry.py
vtelem/data/serializables/EnumRegistry.yaml
vtelem/data/serializables/SerializablePrimitive.yaml
vtelem/data/serializables/UserEnum.yaml
vtelem/enums/__init__.py
vtelem/enums/daemon.py
vtelem/enums/frame.py
vtelem/enums/primitive.py
vtelem/factories/__init__.py
vtelem/factories/daemon_manager.py
vtelem/factories/telemetry_environment.py
vtelem/factories/telemetry_server.py
vtelem/factories/udp_client_manager.py
vtelem/factories/websocket_daemon.py
vtelem/frame/__init__.py
vtelem/frame/channel.py
vtelem/frame/fields.py
vtelem/frame/framer.py
vtelem/frame/message.py
vtelem/frame/processor.py
vtelem/message/__init__.py
vtelem/message/cache.py
vtelem/message/framer.py
vtelem/parsing/__init__.py
vtelem/parsing/encapsulation.py
vtelem/parsing/frames.py
vtelem/registry/__init__.py
vtelem-0.3.5.dist-info/LICENSE
vtelem-0.3.5.dist-info/METADATA
vtelem-0.3.5.dist-info/WHEEL
vtelem-0.3.5.dist-info/entry_points.txt
vtelem-0.3.5.dist-info/top_level.txt
vtelem-0.3.5.dist-info/RECORD
