Metadata-Version: 2.1
Name: vtelem
Version: 0.3.5
Summary: A real-time telemetry library.
Home-page: https://github.com/vkottler/vtelem
Author: Vaughn Kottler
Author-email: Vaughn Kottler <vaughnkottler@gmail.com>
Maintainer-email: Vaughn Kottler <vaughnkottler@gmail.com>
License: UNKNOWN
Platform: UNKNOWN
Classifier: Programming Language :: Python :: 3.7
Classifier: Programming Language :: Python :: 3.8
Classifier: Programming Language :: Python :: 3.9
Classifier: Programming Language :: Python :: 3.10
Classifier: License :: OSI Approved :: MIT License
Requires-Python: >=3.7
License-File: LICENSE
Requires-Dist: cerberus
Requires-Dist: requests
Requires-Dist: websockets
Requires-Dist: netifaces
Requires-Dist: vcorelib
Provides-Extra: test
Requires-Dist: setuptools-wrapper ; extra == 'test'
Requires-Dist: pylint ; extra == 'test'
Requires-Dist: flake8 ; extra == 'test'
Requires-Dist: pytest ; extra == 'test'
Requires-Dist: pytest-cov ; extra == 'test'
Requires-Dist: mypy ; extra == 'test'
Requires-Dist: black ; extra == 'test'
Requires-Dist: isort ; extra == 'test'
